dotrouter/__init__.py
dotrouter/__main__.py
dotrouter/_base_client.py
dotrouter/_client.py
dotrouter/_compat.py
dotrouter/_constants.py
dotrouter/_exceptions.py
dotrouter/_files.py
dotrouter/_legacy_response.py
dotrouter/_models.py
dotrouter/_module_client.py
dotrouter/_qs.py
dotrouter/_resource.py
dotrouter/_response.py
dotrouter/_streaming.py
dotrouter/_types.py
dotrouter/_version.py
dotrouter/pagination.py
dotrouter/py.typed
dotrouter/version.py
dotrouter/_extras/__init__.py
dotrouter/_extras/_common.py
dotrouter/_extras/numpy_proxy.py
dotrouter/_extras/pandas_proxy.py
dotrouter/_utils/__init__.py
dotrouter/_utils/_logs.py
dotrouter/_utils/_proxy.py
dotrouter/_utils/_reflection.py
dotrouter/_utils/_streams.py
dotrouter/_utils/_sync.py
dotrouter/_utils/_transform.py
dotrouter/_utils/_typing.py
dotrouter/_utils/_utils.py
dotrouter/cli/__init__.py
dotrouter/cli/_cli.py
dotrouter/cli/_errors.py
dotrouter/cli/_models.py
dotrouter/cli/_progress.py
dotrouter/cli/_utils.py
dotrouter/cli/_api/__init__.py
dotrouter/cli/_api/_main.py
dotrouter/cli/_api/audio.py
dotrouter/cli/_api/completions.py
dotrouter/cli/_api/files.py
dotrouter/cli/_api/image.py
dotrouter/cli/_api/models.py
dotrouter/cli/_api/chat/__init__.py
dotrouter/cli/_api/chat/completions.py
dotrouter/cli/_tools/__init__.py
dotrouter/cli/_tools/_main.py
dotrouter/cli/_tools/fine_tunes.py
dotrouter/cli/_tools/migrate.py
dotrouter/lib/.keep
dotrouter/lib/_old_api.py
dotrouter/lib/_validators.py
dotrouter/lib/azure.py
dotrouter/lib/streaming/__init__.py
dotrouter/lib/streaming/_assistants.py
dotrouter/resources/__init__.py
dotrouter/resources/batches.py
dotrouter/resources/completions.py
dotrouter/resources/embeddings.py
dotrouter/resources/files.py
dotrouter/resources/images.py
dotrouter/resources/models.py
dotrouter/resources/moderations.py
dotrouter/resources/audio/__init__.py
dotrouter/resources/audio/audio.py
dotrouter/resources/audio/speech.py
dotrouter/resources/audio/transcriptions.py
dotrouter_python-1.35.15.dist-info/METADATA
dotrouter_python-1.35.15.dist-info/WHEEL
dotrouter_python-1.35.15.dist-info/entry_points.txt
dotrouter_python-1.35.15.dist-info/licenses/LICENSE
dotrouter_python-1.35.15.dist-info/RECORD
